palaestrai/__init__.py
palaestrai/py.typed
palaestrai/version.py
palaestrai/agent/__init__.py
palaestrai/agent/actuator_information.py
palaestrai/agent/agent.py
palaestrai/agent/agent_conductor.py
palaestrai/agent/brain.py
palaestrai/agent/brain_dumper.py
palaestrai/agent/dummy_brain.py
palaestrai/agent/dummy_muscle.py
palaestrai/agent/dummy_objective.py
palaestrai/agent/file_brain_dumper.py
palaestrai/agent/learner.py
palaestrai/agent/memory.py
palaestrai/agent/muscle.py
palaestrai/agent/none_brain.py
palaestrai/agent/objective.py
palaestrai/agent/reward_information.py
palaestrai/agent/rollout_worker.py
palaestrai/agent/sensor_information.py
palaestrai/agent/state.py
palaestrai/agent/store_brain_dumper.py
palaestrai/agent/util/__init__.py
palaestrai/agent/util/information_utils.py
palaestrai/agent/util/space_value_utils.py
palaestrai/cli/__init__.py
palaestrai/cli/client_local.py
palaestrai/cli/fortune.py
palaestrai/cli/manager.py
palaestrai/cli/scheduler.py
palaestrai/cli/terminal_formatter.py
palaestrai/core/MDP.py
palaestrai/core/__init__.py
palaestrai/core/basic_state.py
palaestrai/core/event_state_machine.py
palaestrai/core/major_domo_broker.py
palaestrai/core/major_domo_client.py
palaestrai/core/major_domo_multi_client.py
palaestrai/core/major_domo_worker.py
palaestrai/core/runtime_config.py
palaestrai/core/serialisation.py
palaestrai/core/zhelpers.py
palaestrai/core/protocol/__init__.py
palaestrai/core/protocol/agent_conductor_setup_req.py
palaestrai/core/protocol/agent_conductor_setup_rsp.py
palaestrai/core/protocol/agent_setup_req.py
palaestrai/core/protocol/agent_setup_rsp.py
palaestrai/core/protocol/agent_shutdown_req.py
palaestrai/core/protocol/agent_shutdown_rsp.py
palaestrai/core/protocol/agent_update_req.py
palaestrai/core/protocol/agent_update_rsp.py
palaestrai/core/protocol/delayed_result_request.py
palaestrai/core/protocol/delayed_result_response.py
palaestrai/core/protocol/environment_reset_notification_req.py
palaestrai-3.5.8.dist-info/licenses/LICENSE
palaestrai-3.5.8.dist-info/METADATA
palaestrai-3.5.8.dist-info/WHEEL
palaestrai-3.5.8.dist-info/entry_points.txt
palaestrai-3.5.8.dist-info/top_level.txt
palaestrai-3.5.8.dist-info/RECORD
