Metadata-Version: 2.4
Name: palaestrai
Version: 3.5.8
Summary: A Training Ground for Autonomous Agents
Home-page: http://palaestr.ai/
Author: The ARL Developers
Author-email: eric.veith@offis.de
License: LGPLv2
Classifier: Development Status :: 4 - Beta
Classifier: Intended Audience :: Science/Research
Classifier: License :: OSI Approved :: GNU Lesser General Public License v2 (LGPLv2)
Classifier: Natural Language :: English
Classifier: Operating System :: OS Independent
Classifier: Programming Language :: Python
Classifier: Programming Language :: Python :: 3
Classifier: Programming Language :: Python :: 3.10
Classifier: Topic :: Scientific/Engineering
Classifier: Topic :: Scientific/Engineering :: Artificial Intelligence
Requires-Python: >=3.10
License-File: LICENSE
Requires-Dist: click~=8.1.7
Requires-Dist: click-aliases~=1.0.5
Requires-Dist: appdirs~=1.4.4
Requires-Dist: tabulate~=0.9.0
Requires-Dist: semver<4,>=3
Requires-Dist: yamale~=5.2.1
Requires-Dist: ruamel.yaml~=0.18.6
Requires-Dist: simplejson~=3.19.3
Requires-Dist: jsonpickle~=4.0.0
Requires-Dist: uvloop
Requires-Dist: aiomultiprocess~=0.9.1
Requires-Dist: setproctitle~=1.3.4
Requires-Dist: pyzmq~=26.2.0
Requires-Dist: nest_asyncio~=1.6.0
Requires-Dist: pyzstd
Requires-Dist: numpy~=1.26.4
Requires-Dist: pandas~=2.1.4
Requires-Dist: dask[dataframe]~=2024.12.0
Requires-Dist: gymnasium~=1.0.0
Requires-Dist: psycopg2-binary~=2.9.10
Requires-Dist: SQLalchemy~=1.4.50
Requires-Dist: sqlalchemy-utils~=0.41.1
Requires-Dist: pandoc~=2.4
Requires-Dist: GPUtil~=1.4.0
Requires-Dist: psutil~=6.1.0
Requires-Dist: docker~=7.1.0
Provides-Extra: dev
Requires-Dist: Cython~=3.0.11; extra == "dev"
Requires-Dist: tox~=4.23.2; extra == "dev"
Requires-Dist: robotframework~=6.1.1; extra == "dev"
Requires-Dist: robotframework-stacktrace~=0.4.1; extra == "dev"
Requires-Dist: pytest~=8.3.4; extra == "dev"
Requires-Dist: pytest-asyncio~=0.24.0; extra == "dev"
Requires-Dist: pytest-cov~=6.0.0; extra == "dev"
Requires-Dist: coverage~=7.6.9; extra == "dev"
Requires-Dist: lxml~=5.3.0; extra == "dev"
Requires-Dist: mock~=5.1.0; extra == "dev"
Requires-Dist: alchemy-mock~=0.4.3; extra == "dev"
Requires-Dist: black~=24.10.0; extra == "dev"
Requires-Dist: mypy~=1.13.0; extra == "dev"
Requires-Dist: types-click~=7.1.8; extra == "dev"
Requires-Dist: types-setuptools~=75.6.0; extra == "dev"
Requires-Dist: sphinx~=7.4.7; extra == "dev"
Requires-Dist: nbsphinx~=0.9.5; extra == "dev"
Requires-Dist: furo~=2024.8.6; extra == "dev"
Requires-Dist: ipython~=8.30.0; extra == "dev"
Requires-Dist: ipykernel~=6.29.5; extra == "dev"
Requires-Dist: plotly~=5.24.1; extra == "dev"
Requires-Dist: eralchemy2~=1.4.1; extra == "dev"
Provides-Extra: full
Requires-Dist: palaestrai-arsenai~=3.5.0; extra == "full"
Requires-Dist: palaestrai-agents~=3.5.0; extra == "full"
Requires-Dist: palaestrai-environments~=3.5.0; extra == "full"
Requires-Dist: palaestrai-mosaik>=3.5.4; extra == "full"
Requires-Dist: midas-mosaik[arl]~=2.0.0; extra == "full"
Provides-Extra: influx
Requires-Dist: elasticsearch>=7.0.0; extra == "influx"
Requires-Dist: influxdb-client[ciso]; extra == "influx"
Dynamic: author
Dynamic: author-email
Dynamic: classifier
Dynamic: description
Dynamic: home-page
Dynamic: license
Dynamic: license-file
Dynamic: provides-extra
Dynamic: requires-dist
Dynamic: requires-python
Dynamic: summary
